LICENSE
MANIFEST.in
README.rst
setup.cfg
setup.py
versioneer.py
aiopeewee/__init__.py
aiopeewee/_version.py
aiopeewee/context.py
aiopeewee/database.py
aiopeewee/fields.py
aiopeewee/model.py
aiopeewee/mysql.py
aiopeewee/query.py
aiopeewee/result.py
aiopeewee/shortcuts.py
aiopeewee/utils.py
aiopeewee.egg-info/PKG-INFO
aiopeewee.egg-info/SOURCES.txt
aiopeewee.egg-info/dependency_links.txt
aiopeewee.egg-info/not-zip-safe
aiopeewee.egg-info/requires.txt
aiopeewee.egg-info/top_level.txt
aiopeewee/tests/conftest.py
aiopeewee/tests/models.py
aiopeewee/tests/test_manytomany.py
aiopeewee/tests/test_models.py
aiopeewee/tests/test_query_results.py
aiopeewee/tests/test_shortcuts.py
aiopeewee/tests/test_transactions.py
aiopeewee/tests/utils.py