Metadata-Version: 1.1
Name: aiopeewee
Version: 0.4.2
Summary: Async Peewee
Home-page: http://github.com/kszucs/aiopeewee
Author: Krisztian Szucs
Author-email: szucs.krisztian@gmail.com
License: MIT
Keywords: async asyncio peewee orm
Platform: UNKNOWN
Classifier: Intended Audience :: Developers
Classifier: License :: OSI Approved :: MIT License
Classifier: Operating System :: OS Independent
Classifier: Programming Language :: Python
Classifier: Programming Language :: Python :: 3
